quil/__init__.py
quil/__init__.pyi
quil/_quil.cpython-313-x86_64-linux-gnu.so
quil/expression.pyi
quil/instructions.pyi
quil/program.pyi
quil/validation/identifier.pyi
quil/waveforms.pyi
quil-0.34.0.dist-info/METADATA
quil-0.34.0.dist-info/WHEEL
quil-0.34.0.dist-info/RECORD
